imu_api/__init__.py
imu_api/imu_api.py
imu_api/utils.py
imu_api-2.0.0.dist-info/LICENSE
imu_api-2.0.0.dist-info/METADATA
imu_api-2.0.0.dist-info/WHEEL
imu_api-2.0.0.dist-info/top_level.txt
imu_api-2.0.0.dist-info/RECORD
